passogva.py
passogva-1.1.dist-info/LICENSE
passogva-1.1.dist-info/METADATA
passogva-1.1.dist-info/WHEEL
passogva-1.1.dist-info/top_level.txt
passogva-1.1.dist-info/RECORD
